[
    {
        "catgoryName": "Sushi",
        "description": "Sushi is a popular Japanese dish made with vinegared rice and a variety of toppings, such as raw fish, vegetables, and egg.",
        "imageCatagory": "",
        "foods": [
            {
                "foodName": "Nigiri sushi",
                "description": "A traditional form of sushi where a small ball of vinegared rice is topped with slices of raw fish, seafood or vegetables.",
                "price": 350,
                "foodImage": "https://cdn.tasteatlas.com/images/dishes/ef30d84ca9f04834917378c56630c6da.jpg",
                "recommended": false,
                "foodScore": 4
            },
            {
                "foodName": "Maki sushi ",
                "description": "Sushi roll filled with various ingredients like fish, vegetables and rice, wrapped in seaweed.",
                "price": 500,
                "foodImage": "https://img.cuisineaz.com/660x660/2013/12/20/i8238-maki-sushi.jpeg",
                "recommended": false,
                "foodScore": 3
            },
            {
                "foodName": "Sashimi (thinly sliced raw fish)",
                "description": "Thinly sliced raw fish or meat, often served as an appetizer with soy sauce and wasabi.",
                "price": 650,
                "foodImage": "https://cdn.shopify.com/s/files/1/0503/2886/2886/products/AdobeStock_312775781copy.jpg",
                "recommended": false,
                "foodScore": 5
            },
            {
                "foodName": "Temaki sushi",
                "description": "Hand-rolled sushi cones filled with fish and vegetables",
                "price": 650,
                "foodImage": "https://norecipes.com/wp-content/uploads/2017/07/temaki-sushi-2.jpg",
                "recommended": false,
                "foodScore": 5
            },
            {
                "foodName": "Chirashi sushi",
                "description": "Sushi rice topped with various ingredients like fish, vegetables, egg, and meat",
                "price": 890,
                "foodImage": "https://i.blogs.es/d9ae67/chirashizushi2/450_1000.jpg",
                "recommended": false,
                "foodScore": 5
            },
            {
                "foodName": "Inari sushi",
                "description": "Fried tofu pockets filled with sushi rice.",
                "price": 890,
                "foodImage": "https://pickledplum.com/wp-content/uploads/2019/09/inari-sushi-OPTM.jpg",
                "recommended": false,
                "foodScore": 5
            },
            {
                "foodName": "Tamagoyaki",
                "description": "A sweet rolled omelette, often served as a sushi topping",
                "price": 690,
                "foodImage": "https://rasamalaysia.com/wp-content/uploads/2008/11/tamagoyaki-1-320x320.jpg",
                "recommended": false,
                "foodScore": 2
            },
            {
                "foodName": "Eel sushi",
                "description": "Grilled or broiled eel sushi",
                "price": 320,
                "foodImage": "https://www.tasteatlas.com/images/dishes/3b1e8235dde748ec975e8514857876b2.jpg",
                "recommended": false,
                "foodScore": 4
            },
            {
                "foodName": "Unagi sushi",
                "description": "Grilled eel sushi",
                "price": 320,
                "foodImage": "https://c8.alamy.com/comp/R0AA7X/unagi-sushi-or-japanese-eel-grilled-slice-cutting-sushi-in-japanese-style-food-R0AA7X.jpg",
                "recommended": false,
                "foodScore": 4
            },
            {
                "foodName": "Kanpyo sushi",
                "description": "Sushi made with dried gourd",
                "price": 290,
                "foodImage": "http://www.geishasushi.pl/wp-content/uploads/2022/02/GEISHA_SUSHI__HOSOMAKI__KANPYO_MAKI.jpg",
                "recommended": false,
                "foodScore": 1
            }
        ]
    },
    {
        "catgoryName": "Noodles",
        "description": "There are many different types of Japanese noodles, such as ramen, udon, and soba, which are enjoyed in soups, stir-fries, and other dishes.",
        "imageCatagory": "",
        "foods": [
            {
                "foodName": "Ramen",
                "description": "Chinese-style wheat noodles served in a meat or fish-based broth, often flavored with soy sauce or miso, and topped with ingredients such as sliced pork, dried seaweed, and green onions",
                "price": 279,
                "foodImage": "https://www.kitchensanctuary.com/wp-content/uploads/2020/12/Quick-Chicken-Ramen-square-FS-22.jpg",
                "recommended": false,
                "foodScore": 5
            },
            {
                "foodName": "Udon",
                "description": "Thick wheat noodles similar to Italian pasta, often served in a hot soup with various ingredients such as tempura, vegetables, or meat",
                "price": 260,
                "foodImage": "https://www.wandercooks.com/wp-content/uploads/2019/04/udon-noodle-soup-recipe-ft-500x500.jpg",
                "recommended": false,
                "foodScore": 5
            },
            {
                "foodName": "Soba",
                "description": "Thin buckwheat noodles, served either hot in a soup or cold with dipping sauce",
                "price": 320,
                "foodImage": "https://i0.wp.com/cookingtoentertain.com/wp-content/uploads/2020/05/Zaru-Soba-Japanese-Noodles.jpg",
                "recommended": false,
                "foodScore": 4
            },
            {
                "foodName": "Yaki udon",
                "description": "Stir-fried udon noodles with vegetables and meat",
                "price": 390,
                "foodImage": "https://heartfultable.com/wp-content/uploads/2022/03/veggie-yaki-udon-noodles_-2.jpg",
                "recommended": false,
                "foodScore": 2
            },
            {
                "foodName": "Yaki soba",
                "description": "Stir-fried soba noodles with vegetables and meat",
                "price": 390,
                "foodImage": "https://static01.nyt.com/images/2022/01/04/dining/kc-vegetable-yakisoba/kc-vegetable-yakisoba-master768-v4.jpg",
                "recommended": false,
                "foodScore": 3
            },
            {
                "foodName": "Zaru soba",
                "description": "Cold soba noodles served on a bamboo tray, often with a dipping sauce",
                "price": 390,
                "foodImage": "https://125.jinramen.com/wp-content/uploads/2020/07/IMG_5358.png",
                "recommended": false,
                "foodScore": 2
            },
            {
                "foodName": "Kitsune udon",
                "description": "Udon noodles in broth with deep-fried tofu",
                "price": 250,
                "foodImage": "https://i0.wp.com/blog.suvie.com/wp-content/uploads/2020/10/Kitsune-Udon_HERO.jpg?fit=2400%2C1600&ssl=1",
                "recommended": false,
                "foodScore": 1
            },
            {
                "foodName": "Tanuki udon",
                "description": "Udon noodles in broth with tempura scraps",
                "price": 450,
                "foodImage": "https://foodinjapan.org/wp-content/uploads/2022/07/2c7c972e-tanuki_01-1.jpg",
                "recommended": false,
                "foodScore": 4
            },
            {
                "foodName": "Nabeyaki udon",
                "description": "Udon noodles in a hot pot with various ingredients",
                "price": 320,
                "foodImage": "https://img.cybercook.com.br/imagens/receitas/517/nabeyaki-udon.jpg",
                "recommended": false,
                "foodScore": 5
            },
            {
                "foodName": "Kake udon",
                "description": "Udon noodles in a simple broth",
                "price": 290,
                "foodImage": "https://www.justonecookbook.com/wp-content/uploads/2021/10/Kake-Udon-2253-I-500x500.jpg",
                "recommended": false,
                "foodScore": 3
            }
        ]
    },
    {
        "catgoryName": "Seafood",
        "description": "Japan has a long coastline and abundant sea, seafood is very popular and is often served raw as sashimi or grilled as part of a dish.",
        "imageCatagory": "",
        "foods": [
            {
                "foodName": "Sashimi(thinly sliced raw fish)",
                "description": "Thinly sliced raw fish or meat, often served as an appetizer with soy sauce and wasabi",
                "price": 279,
                "foodImage": "https://vanfoodies.files.wordpress.com/2009/05/p1090536s.jpg",
                "recommended": false,
                "foodScore": 5
            },
            {
                "foodName": "Sushi(bite-sized pieces of raw fish served on small balls of sticky rice)",
                "description": "A traditional Japanese dish of vinegared rice served with various ingredients such as raw fish, seafood, and vegetables",
                "price": 200,
                "foodImage": "https://www.butter-n-thyme.com/wp-content/uploads/2022/05/Temari-sushi.jpg",
                "recommended": false,
                "foodScore": 4
            },
            {
                "foodName": "Octopus balls",
                "description": "Ball-shaped Japanese snack made of a wheat flour-based batter and cooked in a special moulded pan",
                "price": 80,
                "foodImage": "https://i.ytimg.com/vi/q25FgyrO0dY/maxresdefault.jpg",
                "recommended": false,
                "foodScore": 5
            },
            {
                "foodName": "Tempura",
                "description": "Deep-fried seafood and vegetables in a light batter",
                "price": 249,
                "foodImage": "https://food.fnr.sndimg.com/content/dam/images/food/fullset/2012/7/25/3/FNM_090112-Shrimp-and-Vegetable-Tempura-Recipe_s4x3.jpg.rend.hgtvcom.616.462.suffix/1371609172818.jpeg",
                "recommended": false,
                "foodScore": 3
            },
            {
                "foodName": "Fugu",
                "description": "Pufferfish, a delicacy in Japan but also considered dangerous if not prepared properly",
                "price": 150,
                "foodImage": "https://savorjapan.com/gg/content_image/fugu-ryouri_tecchiri-nabe.jpg",
                "recommended": false,
                "foodScore": 1
            },
            {
                "foodName": "Kinmedai",
                "description": "Golden eye snapper, a type of fish that is often grilled or steamed",
                "price": 375,
                "foodImage": "https://savorjapan.com/gg/content_image/t0239_003.jpg",
                "recommended": false,
                "foodScore": 3
            },
            {
                "foodName": "Ika",
                "description": "Squid, often grilled or deep-fried and served as sashimi or sushi",
                "price": 230,
                "foodImage": "https://pogogi.com/sites/default/files/yari_ika_nigiri_sushi.jpg",
                "recommended": false,
                "foodScore": 2
            },
            {
                "foodName": "Ebi",
                "description": "Shrimp, often used in tempura or sushi",
                "price": 175,
                "foodImage": "https://www.marutomo.co.jp/wp/wp-content/uploads/2022/02/ebinoumani.jpg",
                "recommended": false,
                "foodScore": 1
            },
            {
                "foodName": "Takuan",
                "description": "Dried yellow pickled radish, often served as a side dish",
                "price": 75,
                "foodImage": "https://www.shutterstock.com/image-photo/takuan-traditional-japanese-marinated-daikon-260nw-2165012785.jpg",
                "recommended": false,
                "foodScore": 1
            },
            {
                "foodName": "Maguro",
                "description": "Tuna, a popular fish used in sushi, sashimi and other dishes",
                "price": 375,
                "foodImage": "https://japannaviuk.files.wordpress.com/2015/04/11081357_10153269522070337_2413089012973776290_n.jpg",
                "recommended": true,
                "foodScore": 5
            }
        ]
    },
    {
        "catgoryName": "Bento",
        "description": "Bento is a traditional Japanese meal that is typically served in a box and contains a variety of items such as rice, fish, meat, and vegetables.",
        "imageCatagory": "",
        "foods": [
            {
                "foodName": "Katsu-don",
                "description": "Deep-fried pork cutlet on rice",
                "price": 220,
                "foodImage": "https://www.sadia.sg/uploads/recipes/20220511024417-2022-05-11recipes023823_md.jpg",
                "recommended": false,
                "foodScore": 4
            },
            {
                "foodName": "Ebi fry-don",
                "description": "Deep-fried shrimp on rice",
                "price": 335,
                "foodImage": "https://www.fuji.co.th/wp-content/uploads/2021/05/149.-090_Ebi-Fry-Don.jpg",
                "recommended": false,
                "foodScore": 3
            },
            {
                "foodName": "Omu-rice",
                "description": "Omelette filled with rice and vegetables",
                "price": 150,
                "foodImage": "https://mykoreankitchen.com/wp-content/uploads/2007/04/3.-Omurice-Rice-Recipe.jpg",
                "recommended": false,
                "foodScore": 4
            },
            {
                "foodName": "Chicken teriyaki-don",
                "description": "Chicken in teriyaki sauce on rice",
                "price": 200,
                "foodImage": "https://rasamalaysia.com/wp-content/uploads/2019/02/chicken-teriyaki-thumb.jpg",
                "recommended": false,
                "foodScore": 5
            },
            {
                "foodName": "Unagi-don",
                "description": "Grilled eel on rice",
                "price": 225,
                "foodImage": "https://media-cdn.tripadvisor.com/media/photo-s/10/62/f5/70/nagoya-unagi-don-bbq.jpg",
                "recommended": false,
                "foodScore": 3
            },
            {
                "foodName": "Kaisen-don",
                "description": "Variety of seafood on rice",
                "price": 300,
                "foodImage": "https://img.wongnai.com/p/400x0/2020/06/06/758ec6bd9e2b498a8229f6cbd424ae31.jpg",
                "recommended": false,
                "foodScore": 4
            },
            {
                "foodName": "Karaage-don",
                "description": "Deep-fried chicken on rice",
                "price": 350,
                "foodImage": "https://sudachirecipes.com/wp-content/uploads/2022/08/karaage-don-thumbnail.jpg",
                "recommended": false,
                "foodScore": 5
            },
            {
                "foodName": "Takikomi gohan",
                "description": "Rice cooked with meat, fish, and vegetables",
                "price": 299,
                "foodImage": "https://okonomikitchen.com/wp-content/uploads/2019/07/takikomigohanricecookerjapanesemixedrice-7.jpg",
                "recommended": false,
                "foodScore": 2
            },
            {
                "foodName": "Kakiage-don",
                "description": "A bowl of rice topped with mixed tempura",
                "price": 260,
                "foodImage": "https://images.summitmedia-digital.com/spotph/images/2017/02/06/tenya1.jpg",
                "recommended": false,
                "foodScore": 4
            }
        ]
    },
    {
        "catgoryName": "Rice dishes",
        "description": "Rice is a staple food in Japan and is often served as the main dish in meals. Some popular rice dishes include donburi (rice bowl dish) and curry rice.",
        "imageCatagory": "",
        "foods": [
            {
                "foodName": "Kare-don",
                "description": "A bowl of rice topped with a spicy curry sauce and meat",
                "price": 220,
                "foodImage": "https://img.taste.com.au/GePUNyer/w1200-h630-cfill/taste/2020/07/katsu-curry-don-163671-2.jpg",
                "recommended": false,
                "foodScore": 5
            },
            {
                "foodName": "Oyakodon",
                "description": "A bowl of rice topped with a sweet and savory chicken and egg mixture",
                "price": 150,
                "foodImage": "https://upload.wikimedia.org/wikipedia/commons/thumb/2/29/Oyakodon_003.jpg/800px-Oyakodon_003.jpg",
                "recommended": false,
                "foodScore": 2
            },
            {
                "foodName": "Kamameshi",
                "description": "Rice cooked with meat and vegetables in a small pot",
                "price": 145,
                "foodImage": "https://gurunavi.com/en/japanfoodie/assets_c/2017/06/kamameshi_top-thumb-300x309-55600.jpg",
                "recommended": false,
                "foodScore": 3
            },
            {
                "foodName": "Onigiri",
                "description": "A simple rice ball often filled with various ingredients such as fish, meat, or vegetables",
                "price": 100,
                "foodImage": "https://www.justonecookbook.com/wp-content/uploads/2017/09/Onigiri-Rice-Balls-3082-500x375.jpg",
                "recommended": false,
                "foodScore": 5
            },
            {
                "foodName": "Gohan",
                "description": "Plain steamed rice",
                "price": 40,
                "foodImage": "https://cdn.cdkitchen.com/recipes/images/2020/08/34215-9235-mx.jpg",
                "recommended": false,
                "foodScore": 2
            }
        ]
    },
    {
        "catgoryName": "Meat dishes",
        "description": "Popular meat dishes include dishes like Yakitori (grilled chicken skewers), karaage (deep-fried chicken) and tonkatsu (deep-fried pork cutlets)",
        "imageCatagory": "",
        "foods": [
            {
                "foodName": "Yakiniku",
                "description": "Grilled meat, usually beef, often cooked at the table on a small gas or charcoal grill",
                "price": 499,
                "foodImage": "https://s3.voyapon.com/wp-content/uploads/2020/08/14182146/yakiniku7.jpg",
                "recommended": true,
                "foodScore": 5
            },
            {
                "foodName": "Tonkatsu",
                "description": "Deep-fried breaded pork cutlet",
                "price": 250,
                "foodImage": "https://tastykitchen.com/recipes/wp-content/uploads/sites/2/2020/04/katsu-landscape-410x273.jpg",
                "recommended": false,
                "foodScore": 3
            },
            {
                "foodName": "Karaage",
                "description": "Deep-fried marinated chicken",
                "price": 140,
                "foodImage": "https://www.foodandwine.com/thmb/8WM1d6lWVkMGbUQWTxoNwxrMwns=/1500x0/filters:no_upscale():max_bytes(150000):strip_icc()/chicken-karaage-FT-RECIPE0621-7c333f0a5c2141e08f0e7f7b9fc1c5de.jpg",
                "recommended": false,
                "foodScore": 2
            },
            {
                "foodName": "Gyudon",
                "description": "Beef and onions on rice",
                "price": 299,
                "foodImage": "https://ryukoch.com/images/food-blog/gyudon-t.jpg",
                "recommended": false,
                "foodScore": 5
            },
            {
                "foodName": "Yakitori",
                "description": "Grilled chicken skewers",
                "price": 150,
                "foodImage": "https://thejapanstore.us/wp-content/uploads/2021/11/shutterstock_579499555-scaled.jpg",
                "recommended": false,
                "foodScore": 3
            },
            {
                "foodName": "Buta no kakuni",
                "description": "Slow-cooked pork belly",
                "price": 199,
                "foodImage": "https://2.bp.blogspot.com/-AWPJ0BmjBgQ/XG4_X7e9ZjI/AAAAAAAAlRI/XbJ560QdA9AdTpvI8NRB4DCR04rACZAHgCKgBGAs/s1600/1-Japanese-Braised-Pork-Recipe-Buta-No-Kakuni-YedyLicious-Manila-FoodBlog-YedyCalaguas.jpg",
                "recommended": false,
                "foodScore": 5
            },
            {
                "foodName": "Kara-age",
                "description": "Deep-fried marinated chicken",
                "price": 299,
                "foodImage": "https://img.buzzfeed.com/thumbnailer-prod-us-east-1/5b2aa37781514ab68f18ae2a1ceb74e6/final3.jpg",
                "recommended": false,
                "foodScore": 4
            },
            {
                "foodName": "Steak",
                "description": "Grilled or pan-fried beef steak",
                "price": 399,
                "foodImage": "https://recipetineats.com/wp-content/uploads/2017/03/Asian-Steak-3-copy.jpg",
                "recommended": false,
                "foodScore": 5
            }
        ]
    },
    {
        "catgoryName": "Sweets",
        "description": "Japan is famous for its traditional sweets like Mochi, Daifuku, and Taiyaki, that are made from glutinous rice flour and sweet fillings like sweet bean paste and matcha cream.",
        "imageCatagory": "",
        "foods": [
            {
                "foodName": "Mochi",
                "description": "Sweet glutinous rice cake often filled with sweet bean paste or ice cream",
                "price": 100,
                "foodImage": "https://thewoksoflife.com/wp-content/uploads/2021/07/red-bean-mochi-10.jpg",
                "recommended": true,
                "foodScore": 5
            },
            {
                "foodName": "Dango",
                "description": "Sweet dumplings made from glutinous rice flour, often served on skewers and topped with a sweet soy glaze",
                "price": 100,
                "foodImage": "https://upload.wikimedia.org/wikipedia/commons/thumb/5/57/Mitarashi_dango_by_denver935.jpg/1200px-Mitarashi_dango_by_denver935.jpg",
                "recommended": false,
                "foodScore": 4
            },
            {
                "foodName": "Matcha",
                "description": "Japanese green tea powder, often used in desserts and sweets",
                "price": 70,
                "foodImage": "https://cdn.shopify.com/s/files/1/1969/5775/articles/9ea37158da837b8b0b466f539d10bedf.jpg",
                "recommended": false,
                "foodScore": 5
            },
            {
                "foodName": "Anmitsu",
                "description": "A sweet dessert made from small cubes of agar jelly, served in a bowl with sweet bean paste, fruit, and syrup",
                "price": 99,
                "foodImage": "https://www.justonecookbook.com/wp-content/uploads/2022/11/Anmitsu-5290-I-1.jpg",
                "recommended": false,
                "foodScore": 5
            },
            {
                "foodName": "Wagashi",
                "description": "Traditional Japanese sweets, often made from sweet bean paste and shaped into intricate designs",
                "price": 70,
                "foodImage": "https://cdn.cheapoguides.com/wp-content/uploads/sites/2/2017/11/iStock-wagashi-studiocasper-471060362.jpg",
                "recommended": false,
                "foodScore": 2
            },
            {
                "foodName": "Daifuku",
                "description": "A sweet glutinous rice cake filled with sweet bean paste",
                "price": 89,
                "foodImage": "https://image.makewebeasy.net/makeweb/0/I1MJQjJJO/Daifuku/Chocolate_Daifuku1.jpeg",
                "recommended": false,
                "foodScore": 4
            },
            {
                "foodName": "Yokan",
                "description": "A thick, jellied dessert made from sweet bean paste, agar, and sugar",
                "price": 79,
                "foodImage": "https://web-japan.org/niponica/images/en/niponica27/07-02.jpg",
                "recommended": false,
                "foodScore": 3
            }
        ]
    },
    {
        "catgoryName": "Street foods",
        "description": "Japanese street foods like Takoyaki and Okonomiyaki are popular and widely available in Japan, often served at festivals and other events.",
        "imageCatagory": "",
        "foods": [
            {
                "name": "Takoyaki",
                "description": "Small ball-shaped snacks filled with diced octopus, tempura scraps, and green onion",
                "price": 79,
                "foodImage": "https://www.tastingtable.com/img/gallery/how-takoyaki-came-to-rule-japans-street-food-scene/l-intro-1669221051.jpg",
                "recommended": false,
                "foodScore": 5
            },
            {
                "name": "Yakiimo",
                "description": "Grilled sweet potatoes often sold from street vendors in the fall",
                "price": 30,
                "foodImage": "https://content.shopback.com/th/wp-content/uploads/2019/07/08093657/1.%E0%B8%94%E0%B8%AD%E0%B8%87%E0%B8%81%E0%B8%B5%E0%B9%89.jpg",
                "recommended": false,
                "foodScore": 3
            },
            {
                "name": "Taiyaki",
                "description": "Fish-shaped waffle filled with sweet red bean paste or custard",
                "price": 50,
                "foodImage": "https://sudachirecipes.com/wp-content/uploads/2022/02/Taiyaki-sq.png",
                "recommended": false,
                "foodScore": 4
            },
            {
                "name": "Okonomiyaki",
                "description": "Savory pancake filled with various ingredients such as meat, seafood, and vegetables",
                "price": 60,
                "foodImage": "https://upload.wikimedia.org/wikipedia/commons/thumb/5/59/Okonomiyaki_001.jpg/1200px-Okonomiyaki_001.jpg",
                "recommended": false,
                "foodScore": 5
            },
            {
                "name": "Ikayaki",
                "description": "Grilled squid often sold from street vendors",
                "price": 40,
                "foodImage": "https://asianinspirations.com.au/wp-content/uploads/2018/07/R00728_Ikayaki.jpg",
                "recommended": false,
                "foodScore": 3
            },
            {
                "name": "Kakigoori",
                "description": "Shaved ice topped with sweet syrups and condensed milk",
                "price": 55,
                "foodImage": "https://upload.wikimedia.org/wikipedia/commons/a/a1/Macha_kakigori_snow_cone.jpg",
                "recommended": false,
                "foodScore": 5
            }
        ]
    }
]